numnerd/__init__.py
numnerd/constants.py
numnerd/primes.py
numnerd/recreational.py
numnerd/sequences.py
numnerd-0.0.3.dist-info/licenses/LICENSE
numnerd-0.0.3.dist-info/METADATA
numnerd-0.0.3.dist-info/WHEEL
numnerd-0.0.3.dist-info/top_level.txt
numnerd-0.0.3.dist-info/RECORD
