Metadata-Version: 2.4
Name: numnerd
Version: 0.0.3
Summary: A Python library for nerdy mathematical functions and number theory.
Author-email: Max <mail@maxduckwitz.de>
Project-URL: Homepage, https://github.com/mduckwitz/numnerd
Classifier: Programming Language :: Python :: 3
Classifier: License :: OSI Approved :: MIT License
Classifier: Operating System :: OS Independent
Requires-Python: >=3.7
License-File: LICENSE
Dynamic: license-file
